{
	"name": "DelimitedText2",
	"properties": {
		"linkedServiceName": {
			"referenceName": "AzureBlobStorage5",
			"type": "LinkedServiceReference"
		},
		"annotations": [],
		"type": "DelimitedText",
		"typeProperties": {
			"location": {
				"type": "AzureBlobStorageLocation",
				"container": "archivefiles"
			},
			"columnDelimiter": "|",
			"escapeChar": "\\",
			"firstRowAsHeader": true,
			"quoteChar": "\""
		},
		"schema": [
			{
				"name": "EMPNO|ENAME|JOB|MGR|HIREDATE|SAL|COMM|DEPTNO",
				"type": "String"
			}
		]
	},
	"type": "Microsoft.DataFactory/factories/datasets"
}